LoveShouko/__init__.py
LoveShouko/test1.py
LoveShouko-0.0.5.dist-info/LICENSE.txt
LoveShouko-0.0.5.dist-info/METADATA
LoveShouko-0.0.5.dist-info/WHEEL
LoveShouko-0.0.5.dist-info/entry_points.txt
LoveShouko-0.0.5.dist-info/top_level.txt
LoveShouko-0.0.5.dist-info/RECORD
