Metadata-Version: 2.1
Name: LoveShouko
Version: 0.0.5
Summary: Auto check in.
Home-page: https://github.com/LoveNishimiyaShouko/LoveShouko
Author: LoveNishimiyaShouko
Author-email: LoveNishimiyaShouko@LoveNishimiyaShouko.LoveNishimiyaShouko
License: AGPLv3
Project-URL: Documentation, https://github.com/LoveNishimiyaShouko/LoveShouko/tree/main/docs
Project-URL: Source, https://github.com/LoveNishimiyaShouko/LoveShouko/tree/main/code
Keywords: auto,check in,auto check in
Platform: UNKNOWN
Classifier: Development Status :: 5 - Production/Stable
Classifier: License :: OSI Approved :: GNU Affero General Public License v3 or later (AGPLv3+)
Classifier: Operating System :: OS Independent
Classifier: Programming Language :: Python
Requires-Python: >=3
Requires-Dist: requests
